{
  "$schema": "https://biomejs.dev/schemas/2.4.10/schema.json",
  "vcs": {
    "enabled": true,
    "clientKind": "git",
    "useIgnoreFile": true
  },
  "formatter": {
    "enabled": true,
    "indentStyle": "space",
    "indentWidth": 2
  },
  "linter": {
    "enabled": true,
    "rules": {
      "recommended": true,
      "suspicious": {
        "noExplicitAny": "warn"
      },
      "correctness": {
        "noUnusedImports": "error",
        "noUnusedVariables": "warn"
      }
    }
  },
  "assist": { "actions": { "source": { "organizeImports": "on" } } },
  "javascript": {
    "formatter": {
      "quoteStyle": "single",
      "semicolons": "asNeeded",
      "trailingCommas": "all"
    }
  },
  "json": {
    "formatter": {
      "trailingCommas": "none"
    }
  },
  "overrides": [
    {
      "includes": ["**/tests/**/*.test.ts", "**/tests/**/*.test.tsx"],
      "linter": {
        "rules": {
          "suspicious": {
            "noExplicitAny": "off"
          }
        }
      }
    }
  ]
}
